{"event": {"sets": {"pageInfo": {"totalPages": 1, "total": 3}, "nodes": [{"id": 91981992, "state": 3, "round": 2, "fullRoundText": "Final", "completedAt": 1753701061, "winnerId": 20580590, "slots": [{"id": "91981992-0", "entrant": {"id": 20580563, "name": "FNG | SHB", "participants": [{"id": 18947963, "gamerTag": "SHB", "prefix": "FNG", "user": {"location": {"city": null, "state": null, "country": "United States"}}, "player": {"id": 3194253, "gamerTag": "SHB", "prefix": "FNG", "user": {"location": {"city": null, "state": null, "country": "United States"}}}}]}, "standing": {"placement": 2, "stats": {"score": {"value": 1}}}}, {"id": "91981992-1", "entrant": {"id": 20580590, "name": "FNG | S0URCEC0DE", "participants": [{"id": 18947989, "gamerTag": "S0URCEC0DE", "prefix": "FNG", "user": {"location": {"city": "Macon", "state": "GA", "country": "United States"}}, "player": {"id": 2699776, "gamerTag": "S0URCEC0DE", "prefix": "FNG", "user": {"location": {"city": "Macon", "state": "GA", "country": "United States"}}}}]}, "standing": {"placement": 1, "stats": {"score": {"value": 3}}}}], "games": null}, {"id": 91981990, "state": 3, "round": 1, "fullRoundText": "Semi-Final", "completedAt": 1753701008, "winnerId": 20580563, "slots": [{"id": "91981990-0", "entrant": {"id": 20580563, "name": "FNG | SHB", "participants": [{"id": 18947963, "gamerTag": "SHB", "prefix": "FNG", "user": {"location": {"city": null, "state": null, "country": "United States"}}, "player": {"id": 3194253, "gamerTag": "SHB", "prefix": "FNG", "user": {"location": {"city": null, "state": null, "country": "United States"}}}}]}, "standing": {"placement": 1, "stats": {"score": {"value": 4}}}}, {"id": "91981990-1", "entrant": {"id": 20820411, "name": "FNG | Miss Suzy", "participants": [{"id": 19159557, "gamerTag": "Miss Suzy", "prefix": "FNG", "user": null, "player": {"id": 4897183, "gamerTag": "Miss Suzy", "prefix": "FNG", "user": null}}]}, "standing": {"placement": 2, "stats": {"score": {"value": 0}}}}], "games": null}, {"id": 91981991, "state": 3, "round": 1, "fullRoundText": "Semi-Final", "completedAt": 1753701039, "winnerId": 20580590, "slots": [{"id": "91981991-0", "entrant": {"id": 20580590, "name": "FNG | S0URCEC0DE", "participants": [{"id": 18947989, "gamerTag": "S0URCEC0DE", "prefix": "FNG", "user": {"location": {"city": "Macon", "state": "GA", "country": "United States"}}, "player": {"id": 2699776, "gamerTag": "S0URCEC0DE", "prefix": "FNG", "user": {"location": {"city": "Macon", "state": "GA", "country": "United States"}}}}]}, "standing": {"placement": 1, "stats": {"score": {"value": 3}}}}, {"id": "91981991-1", "entrant": {"id": 20786471, "name": "forvr | forevertrent", "participants": [{"id": 19130018, "gamerTag": "forevertrent", "prefix": "forvr", "user": {"location": {"city": "Macon", "state": "GA", "country": "United States"}}, "player": {"id": 4276309, "gamerTag": "forevertrent", "prefix": "forvr", "user": {"location": {"city": "Macon", "state": "GA", "country": "United States"}}}}]}, "standing": {"placement": 2, "stats": {"score": {"value": 1}}}}], "games": null}]}}}