{"event": {"standings": {"pageInfo": {"totalPages": 1, "total": 6}, "nodes": [{"id": 84073987, "placement": 1, "entrant": {"id": 20827905, "name": "carlop"}}, {"id": 84073985, "placement": 2, "entrant": {"id": 20825035, "name": "Whaley"}}, {"id": 84073984, "placement": 3, "entrant": {"id": 20823530, "name": "red dot"}}, {"id": 84073982, "placement": 4, "entrant": {"id": 20823433, "name": "KSU | colorful\u029a\u025e"}}, {"id": 84073986, "placement": 5, "entrant": {"id": 20827461, "name": "SaggyMilkJug"}}, {"id": 84073983, "placement": 6, "entrant": {"id": 20823438, "name": "KSU | Subzero"}}]}}}