{"phase": {"seeds": {"pageInfo": {"totalPages": 1, "total": 8}, "nodes": [{"id": 36714756, "seedNum": 1, "entrant": {"id": 21334226, "name": "LBE | CC | Savant", "participants": [{"id": 19612132, "gamerTag": "Savant", "prefix": "LBE | CC", "user": {"location": {"city": "Athens", "state": "GA", "country": "United States"}}, "player": {"id": 1944044, "gamerTag": "Savant", "prefix": "LBE | CC", "user": {"location": {"city": "Athens", "state": "GA", "country": "United States"}}}}]}}, {"id": 36783203, "seedNum": 4, "entrant": {"id": 21382528, "name": "Bany05", "participants": [{"id": 19655698, "gamerTag": "Bany05", "prefix": null, "user": {"location": {"city": null, "state": null, "country": null}}, "player": {"id": 2637493, "gamerTag": "Bany05", "prefix": null, "user": {"location": {"city": null, "state": null, "country": null}}}}]}}, {"id": 36763456, "seedNum": 3, "entrant": {"id": 21368528, "name": "67 | Omar", "participants": [{"id": 19643331, "gamerTag": "Omar", "prefix": "67", "user": {"location": {"city": null, "state": "GA", "country": "United States"}}, "player": {"id": 4300029, "gamerTag": "Omar", "prefix": "", "user": {"location": {"city": null, "state": "GA", "country": "United States"}}}}]}}, {"id": 36759399, "seedNum": 5, "entrant": {"id": 21365315, "name": "jack | jazzman", "participants": [{"id": 19640463, "gamerTag": "jazzman", "prefix": "jack", "user": {"location": {"city": "Athens", "state": "GA", "country": "United States"}}, "player": {"id": 3883272, "gamerTag": "jazzman", "prefix": "jack", "user": {"location": {"city": "Athens", "state": "GA", "country": "United States"}}}}]}}, {"id": 36759164, "seedNum": 6, "entrant": {"id": 21365123, "name": "CC UGA | Infinite_Radiance", "participants": [{"id": 19640303, "gamerTag": "Infinite_Radiance", "prefix": "CC UGA", "user": {"location": {"city": null, "state": "GA", "country": "United States"}}, "player": {"id": 4926508, "gamerTag": "Infinite_Radiance", "prefix": "CC UGA", "user": {"location": {"city": null, "state": "GA", "country": "United States"}}}}]}}, {"id": 36714772, "seedNum": 7, "entrant": {"id": 21334239, "name": "CC | Vertebrae", "participants": [{"id": 19612140, "gamerTag": "Vertebrae", "prefix": "CC", "user": {"location": {"city": "Athens", "state": "GA", "country": "United States"}}, "player": {"id": 1583946, "gamerTag": "Vertebrae", "prefix": "CC", "user": {"location": {"city": "Athens", "state": "GA", "country": "United States"}}}}]}}, {"id": 36765826, "seedNum": 2, "entrant": {"id": 21370350, "name": "DeDeDeadly", "participants": [{"id": 19645021, "gamerTag": "DeDeDeadly", "prefix": "", "user": {"location": {"city": null, "state": null, "country": "United States"}}, "player": {"id": 2267772, "gamerTag": "DeDeDeadly", "prefix": "", "user": {"location": {"city": null, "state": null, "country": "United States"}}}}]}}, {"id": 36771749, "seedNum": 8, "entrant": {"id": 21374698, "name": "UGA | | samtwo", "participants": [{"id": 19648785, "gamerTag": "samtwo", "prefix": "UGA |", "user": {"location": {"city": "Athens", "state": "GA", "country": "United States"}}, "player": {"id": 1246662, "gamerTag": "samtwo", "prefix": "UGA |", "user": {"location": {"city": "Athens", "state": "GA", "country": "United States"}}}}]}}]}}}